hypothesis_auto_draw/__init__.py
hypothesis_auto_draw/hypothesis_auto_draw.py
hypothesis_auto_draw-0.1.5.dist-info/METADATA
hypothesis_auto_draw-0.1.5.dist-info/WHEEL
hypothesis_auto_draw-0.1.5.dist-info/top_level.txt
hypothesis_auto_draw-0.1.5.dist-info/RECORD
