Metadata-Version: 2.1
Name: hypothesis-auto-draw
Version: 0.1.5
Summary: Provides the `auto_draw_map` and `auto_draw_flatmap` functions
Home-page: UNKNOWN
Author: Bao Wei
Author-email: baowei.ur521@gmail.com
License: MIT
Platform: UNKNOWN
Requires-Python: >=3.8
Requires-Dist: functional-itertools (>=0.11)
Requires-Dist: hypothesis (>=5.16)
